Metadata-Version: 1.1
Name: flask-app-core
Version: 1.2.0
Summary: Flask app core
Home-page: https://github.com/aiscenblue/flask-app-core
Author: Jeffrey Marvin Forones
Author-email: aiscenblue@gmail.com
License: MIT
Keywords: flask,clask_app_core,flask_app_builder
Platform: UNKNOWN
Classifier: Development Status :: 5 - Production/Stable
Classifier: Intended Audience :: Developers
Classifier: Topic :: Software Development :: Build Tools
Classifier: License :: OSI Approved :: MIT License
Classifier: Programming Language :: Python :: 2
Classifier: Programming Language :: Python :: 2.6
Classifier: Programming Language :: Python :: 2.7
Classifier: Programming Language :: Python :: 3
Classifier: Programming Language :: Python :: 3.2
Classifier: Programming Language :: Python :: 3.3
Classifier: Programming Language :: Python :: 3.4
Classifier: Framework :: Flask
